smithy_aws_core/__init__.py
smithy_aws_core/py.typed
smithy_aws_core/traits.py
smithy_aws_core/utils.py
smithy_aws_core/aio/__init__.py
smithy_aws_core/aio/protocols.py
smithy_aws_core/auth/__init__.py
smithy_aws_core/auth/sigv4.py
smithy_aws_core/endpoints/__init__.py
smithy_aws_core/endpoints/standard_regional.py
smithy_aws_core/identity/__init__.py
smithy_aws_core/identity/chain.py
smithy_aws_core/identity/components.py
smithy_aws_core/identity/container.py
smithy_aws_core/identity/environment.py
smithy_aws_core/identity/imds.py
smithy_aws_core/identity/static.py
smithy_aws_core/interceptors/__init__.py
smithy_aws_core/interceptors/user_agent.py
smithy_aws_core/interfaces/__init__.py
smithy_aws_core-0.1.0.dist-info/METADATA
smithy_aws_core-0.1.0.dist-info/WHEEL
smithy_aws_core-0.1.0.dist-info/licenses/NOTICE
smithy_aws_core-0.1.0.dist-info/RECORD
